orglearn/__init__.py
orglearn/cli.py
orglearn/preprocessor.py
orglearn/utils.py
orglearn/anki/__init__.py
orglearn/anki/anki_convertor.py
orglearn/anki/node_convertor.py
orglearn/mind_map/__init__.py
orglearn/mind_map/map_convertor.py
orglearn/mind_map/backend/__init__.py
orglearn/mind_map/backend/backend.py
orglearn/mind_map/backend/backends.py
orglearn/mind_map/backend/graphviz.py
tests/__init__.py
tests/conftest.py
tests/test_anki.py
tests/test_preprocessor.py
orglearn-1.1.5.dist-info/LICENSE
orglearn-1.1.5.dist-info/METADATA
orglearn-1.1.5.dist-info/WHEEL
orglearn-1.1.5.dist-info/entry_points.txt
orglearn-1.1.5.dist-info/top_level.txt
orglearn-1.1.5.dist-info/RECORD
