Metadata-Version: 2.1
Name: orglearn
Version: 1.1.5
Summary: Tool to learn from your org-mode notes
Home-page: https://github.com/MatejKastak/orglearn
Author: Matej Kastak
Author-email: matej.kastak@gmail.com
License: MIT
Platform: UNKNOWN
Classifier: Development Status :: 3 - Alpha
Classifier: Environment :: Console
Classifier: Intended Audience :: Developers
Classifier: Intended Audience :: Education
Classifier: License :: OSI Approved :: MIT License 
Classifier: Natural Language :: English
Classifier: Operating System :: MacOS :: MacOS X
Classifier: Operating System :: POSIX :: Linux
Classifier: Programming Language :: Python :: 3
Classifier: Programming Language :: Python :: 3.3
Classifier: Programming Language :: Python :: 3.4
Classifier: Programming Language :: Python :: 3.7
Classifier: Programming Language :: Python :: 3.8
Classifier: Topic :: Education
Requires-Dist: Click (==7.0)
Requires-Dist: anki (==2.1.44)
Requires-Dist: colour (==0.1.5)
Requires-Dist: genanki (==0.8.0)
Requires-Dist: graphviz (==0.13.2)
Requires-Dist: orgparse (==0.1.2)
Requires-Dist: pypandoc (==1.4)
Provides-Extra: all
Requires-Dist: pytest (==6.2.4) ; extra == 'all'
Requires-Dist: black (==19.10b0) ; extra == 'all'
Requires-Dist: pre-commit (==2.0.1) ; extra == 'all'
Requires-Dist: ipdb (==0.13.7) ; extra == 'all'
Provides-Extra: dev
Requires-Dist: pytest (==6.2.4) ; extra == 'dev'
Requires-Dist: black (==19.10b0) ; extra == 'dev'
Requires-Dist: pre-commit (==2.0.1) ; extra == 'dev'
Requires-Dist: ipdb (==0.13.7) ; extra == 'dev'
